dash_offline_detect_plugin/__init__.py
dash_offline_detect_plugin-0.1.3.dist-info/licenses/LICENSE
dash_offline_detect_plugin-0.1.3.dist-info/METADATA
dash_offline_detect_plugin-0.1.3.dist-info/WHEEL
dash_offline_detect_plugin-0.1.3.dist-info/top_level.txt
dash_offline_detect_plugin-0.1.3.dist-info/RECORD
