Metadata-Version: 2.4
Name: dash-offline-detect-plugin
Version: 0.1.3
Summary: Offline detect plugin for Dash applications using Dash Hooks.
Home-page: https://github.com/CNFeffery/dash-offline-detect-plugin
Author: CNFeffery
Author-email: fefferypzy@gmail.com
License-File: LICENSE
Requires-Dist: dash>=3.0.4
Dynamic: author
Dynamic: author-email
Dynamic: description
Dynamic: description-content-type
Dynamic: home-page
Dynamic: license-file
Dynamic: requires-dist
Dynamic: summary
